Workbook

Sheet Dashboard_PL
B2: ORCA WATER PLANT - FINANCIAL & OPERATIONAL DASHBOARD
B3: Real-Time Business Performance & Profit & Loss Summary (FY 2026 - 2027)
B5: TOTAL GROSS SALES & DISCOUNTS | E5: TOTAL COST OF GOODS SOLD (COGS) | H5: GROSS PROFIT (AFTER COGS & DIRECT EXP)
B6: 192320 | E6: =Products!G6 -> 136053.54 | H6: =C13 -> 136053.54
B9: P&L Statement Category | C9: Amount (PKR) | E9: Notes & Reconciled Sources
B10: Total Gross Sales Revenue | C10: 192320 | E10: Detailed Sales Report Total Gross Sales
B11: Less: Total Discounts Allowed | C11: -6190 | E11: Explicit Invoice & Rate-Based Discounts
B12: Net Sales Revenue | C12: =C10+C11 -> 186130 | E12: Net Sales Realized (PKR 186,130.00)
B13: Less: Cost of Goods Sold (COGS) | C13: =Products!G6 -> 136053.54 | E13: Inventory Report (1500ml & 500ml Pure/Mix)
B14: PRODUCT GROSS MARGIN | C14: =C12-C13 -> 50076.46 | E14: Total Product Contribution
B15: Less: Direct Plant Operating Expenses | C15: =Direct_Operating_Expenses!E27 -> 11760 | E15: Fuel, Electricity, Gas, Software
B16: GROSS PROFIT | C16: =C14-C15 -> 38316.46 | E16: Net Business Gross Profit
B17: Less: Indirect Expenses (Personal Owner Draws) | C17: =Owners_Draws!E4 -> 20350 | E17: Profit Deductions / Owner Income Withdrawals
B18: NET PROFIT / REMAINING CASH FLOW | C18: =C16-C17 -> 17966.46 | E18: Reinvestable Net Plant Balance
B19: Total Outstanding Client Receivables (Unpaid Invoices) | C19: =Unpaid_Invoices!F11 -> 28470 | E19: 9 Active Unpaid Invoices across 9 Clients
B20: Total Cash Payments Collected to Date | C20: 157660 | E20: Collected Sales Revenue
B21: Remaining Unsold Finished Goods Inventory Valuation | C21: =Products!I6 -> 132173.46 | E21: 34 Pcs 500ml Pure, 220 Pcs 1500ml Pure, etc.

Sheet Customers
A1: Sr No. | B1: Organization Name | C1: Client Category | D1: Contact Person | E1: Contact Number | F1: Email | G1: Address | H1: Tax ID | I1: Business Details | J1: Shipping Address
A2: 1 | B2: Abdullah Cold Corner | C2: Special Customer | D2: Amir Bhai | E2: 0301 6265080 | F2: - | G2: Jassar Bypass, Narowal | H2: - | I2: - | J2: Amir Bhai Abdullah Cold Corner 0301 6265080
A3: 2 | B3: Abid Karyana Store | C3: - | D3: Abid Karyana Store | E3: 0333 8868876 | F3: - | G3: Mohalla Abbas Nagar | H3: - | I3: - | J3: Abid Karyana Store 0333 8868876
A4: 3 | B4: Abrar Butt | C4: - | D4: - | E4: - | F4: - | G4: - | H4: - | I4: - | J4: -
A5: 4 | B5: Adnan Pan Shop | C5: - | D5: - | E5: - | F5: - | G5: Opposite Roshan Palace, Narowal | H5: - | I5: - | J5: -
A6: 5 | B6: Al Khair Pharmacy | C6: - | D6: - | E6: 03235626060 | F6: - | G6: Zafarwal Bypass, Narowal | H6: - | I6: - | J6: -
A7: 6 | B7: Al Raheem Unity Store | C7: - | D7: - | E7: 03328384666 | F7: - | G7: Opposite Al Raheem Residentia | H7: - | I7: - | J7: -
A8: 7 | B8: Ali Bhai Tuck Shop | C8: - | D8: Mohammad Ali | E8: 03046803341 | F8: - | G8: Sabzi Mandi Narowal | H8: - | I8: - | J8: -
A9: 8 | B9: Allah Rakha Pan Shop | C9: - | D9: - | E9: - | F9: - | G9: Baddomalhi | H9: - | I9: - | J9: -
A10: 9 | B10: Amir Stationary | C10: - | D10: - | E10: - | F10: - | G10: Opposite RCS College, Circular Road, Narowal | H10: - | I10: - | J10: -
A11: 10 | B11: Anwar Butt | C11: - | D11: - | E11: - | F11: - | G11: Behind FDPP Pharmacy, Narowal | H11: - | I11: - | J11: -
A12: 11 | B12: Anwar Karyana Store | C12: - | D12: - | E12: +92 300 7772385 | F12: - | G12: Old Kuchehry Road | H12: - | I12: - | J12: -
A13: 12 | B13: AR Super Store | C13: - | D13: - | E13: 03456941017 | F13: - | G13: Near University Of Narowal | H13: - | I13: - | J13: -
... A57: 56 | B57: Zam Zam Store | C57: - | D57: Mohammas Anas | E57: 03034960338 | F57: - | G57: Sialkot Phatak, Narowal | H57: - | I57: - | J57: Mohammas Anas Sialkot Phatak, Narowa

Sheet Raw_Materials
A1: Item Code | B1: Raw Material Item | C1: Unit Type | D1: Total Purchased / Available Stock | E1: Consumed Stock | F1: Current Stock Balance | G1: Unit Cost (PKR) | H1: Total Remaining Valuation (PKR)
A2: RM-01 | B2: 500ml Mix Bottle | C2: Pcs | D2: 2400 | E2: 360 | F2: =D2-E2 -> 2040 | G2: 9.23 | H2: =F2*G2 -> 18829.2
A3: RM-02 | B3: 1500ml Mix Bottle | C3: Pcs | D3: 2100 | E3: 414 | F3: =D3-E3 -> 1686 | G3: 15 | H3: =F3*G3 -> 25290
A4: RM-03 | B4: 500ml Pure Bottle | C4: Pcs | D4: 3600 | E4: 3192 | F4: =D4-E4 -> 408 | G4: 13.8 | H4: =F4*G4 -> 5630.4
A5: RM-04 | B5: 1500ml Pure Bottle | C5: Pcs | D5: 3000 | E5: 1680 | F5: =D5-E5 -> 1320 | G5: 24 | H5: =F5*G5 -> 31680
A6: RM-05 | B6: 500ml Label | C6: Pcs | D6: 39979 | E6: 3552 | F6: =D6-E6 -> 36427 | G6: 1.92 | H6: =F6*G6 -> 69939.84
A7: RM-06 | B7: 1500ml Label | C7: Pcs | D7: 16641 | E7: 2094 | F7: =D7-E7 -> 14547 | G7: 4.3 | H7: =F7*G7 -> 62552.1
A8: RM-07 | B8: 500ml Mix Shrink Film | C8: Pcs | D8: 800 | E8: 30 | F8: =D8-E8 -> 770 | G8: 14.1 | H8: =F8*G8 -> 10857
A9: RM-08 | B9: 1500ml Mix Shrink Film | C9: Pcs | D9: 790 | E9: 69 | F9: =D9-E9 -> 721 | G9: 15.5 | H9: =F9*G9 -> 11175.5
A10: RM-09 | B10: 500ml Pure Shrink Film | C10: Pcs | D10: 990 | E10: 266 | F10: =D10-E10 -> 724 | G10: 22.6 | H10: =F10*G10 -> 16362.4
A11: RM-10 | B11: 1500ml Pure Shrink Film | C11: Pcs | D11: 835 | E11: 280 | F11: =D11-E11 -> 555 | G11: 26.81 | H11: =F11*G11 -> 14879.55
A12: RM-11 | B12: Caps (Universal) | C12: Pcs | D12: 16000 | E12: 5646 | F12: =D12-E12 -> 10354 | G12: 2 | H12: =F12*G12 -> 20708
B13: TOTAL RAW MATERIALS | D13: =SUM(D2:D12) -> 87135 | E13: =SUM(E2:E12) -> 17583 | F13: =SUM(F2:F12) -> 69552 | H13: =SUM(H2:H12) -> 287903.99

Sheet Sales_Orders
A1: Date | B1: Invoice No. | C1: Client Name | D1: Product Name | E1: Quantity (Bundles) | F1: Unit Rate (PKR) | G1: Discount (PKR) | H1: Taxable Amount (PKR) | I1: Amount After Tax (PKR)
A3: 23-08-2026 | B3: INV2 | C3: Zam Zam Store | D3: 1500 ml Pure PET | E3: 2 | F3: 310 | G3: 0 | H3: 620 | I3: 620
A4: 23-08-2026 | B4: INV2 | C4: Zam Zam Store | D4: 500 ml Pure PET | E4: 3 | F4: 320 | G4: 0 | H4: 960 | I4: 960
A5: 08-08-2026 | B5: INV3 | C5: Butt Choice | D5: 500 ml Pure PET | E5: 3 | F5: 320 | G5: 0 | H5: 960 | I5: 960
A6: 08-08-2026 | B6: INV3 | C6: Butt Choice | D6: 1500 ml Pure PET | E6: 3 | F6: 310 | G6: 0 | H6: 930 | I6: 930
A7: 24-08-2026 | B7: INV4 | C7: Friends Pharmacy | D7: 1500 ml Pure PET | E7: 5 | F7: 310 | G7: 0 | H7: 1550 | I7: 1550
A8: 24-08-2026 | B8: INV4 | C8: Friends Pharmacy | D8: 500 ml Pure PET | E8: 5 | F8: 320 | G8: 0 | H8: 1600 | I8: 1600
A9: 24-08-2026 | B9: INV5 | C9: Sauce & Boss Restaurant | D9: 1500 ml Pure PET | E9: 5 | F9: 310 | G9: 0 | H9: 1550 | I9: 1550
A10: 24-08-2026 | B10: INV5 | C10: Sauce & Boss Restaurant | D10: 500 ml Pure PET | E10: 5 | F10: 320 | G10: 0 | H10: 1600 | I10: 1600
A11: 24-08-2026 | B11: INV6 | C11: Talha Maqbool | D11: 1500 ml Pure PET | E11: 12 | F11: 310 | G11: 0 | H11: 3720 | I11: 3720
A12: 24-08-2026 | B12: INV6 | C12: Talha Maqbool | D12: Overall Invoice | E12: 0 | F12: 0 | G12: 120 | H12: 0 | I12: -120
A13: 24-08-2026 | B13: INV7 | C13: Care Pharmacy | D13: 1500 ml Pure PET | E13: 2 | F13: 310 | G13: 0 | H13: 620 | I13: 620
A14: 24-08-2026 | B14: INV7 | C14: Care Pharmacy | D14: 500 ml Pure PET | E14: 2 | F14: 320 | G14: 0 | H14: 640 | I14: 640
... A196: 22-10-2026 | B196: INV#93 | C196: Sajjad Sahab | D196: 1500 ml Pure PET | E196: 10 | F196: 310 | G196: 0 | H196: 3100 | I196: 3100
A197: 22-10-2026 | B197: INV#93 | C197: TOTAL SALES | D197: Overall Invoice | E197: =SUM(E2:E196) -> 645 | F197: 0 | G197: =SUM(G2:G196) -> 6090 | H197: =SUM(H2:H196) -> 192320 | I197: =SUM(I2:I196) -> 186230

Sheet Products
A1: Product Code / SKU | B1: Product Name | C1: Opening Stock (Bundles) | D1: Unit COGS / Buy Rate (PKR) | E1: Opening Valuation (PKR) | F1: Sold Qty (Bundles) | G1: COGS Amount Sold (PKR) | H1: Remaining Stock (Bundles) | I1: Remaining Stock Valuation (PKR)
A2: PROD-01 | B2: 1500 ml Mix PET | C2: 350 | D2: 143.3 | E2: =C2*D2 -> 50155 | F2: 69 | G2: =F2*D2 -> 9887.7 | H2: =C2-F2 -> 281 | I2: =H2*D2 -> 40267.3
A3: PROD-02 | B3: 1500 ml Pure PET | C3: 500 | D3: 208.6 | E3: =C3*D3 -> 104300 | F3: 280 | G3: =F3*D3 -> 58408 | H3: =C3-F3 -> 220 | I3: =H3*D3 -> 45892
A4: PROD-03 | B4: 500 ml Mix PET | C4: 250 | D4: 172.8 | E4: =C4*D4 -> 43200 | F4: 30 | G4: =F4*D4 -> 5184 | H4: =C4-F4 -> 220 | I4: =H4*D4 -> 38016
A5: PROD-04 | B5: 500 ml Pure PET | C5: 300 | D5: 235.24 | E5: =C5*D5 -> 70572 | F5: 266 | G5: =F5*D5 -> 62573.84 | H5: =C5-F5 -> 34 | I5: =H5*D5 -> 7998.16
B6: TOTAL INVENTORY VALUATION | E6: =SUM(E2:E5) -> 268227 | G6: =SUM(G2:G5) -> 136053.54 | I6: =SUM(I2:I5) -> 132173.46

Sheet Product_Wise_Sales
A1: Month / Period | B1: Product Name | C1: Quantity Sold (Pcs) | D1: Total Amount (PKR)
A2: Aug 2026 | B2: 1500 ml Mix PET | C2: 38 | D2: 7600
A3: Aug 2026 | B3: 1500 ml Pure PET | C3: 49 | D3: 15190
A4: Aug 2026 | B4: 500 ml Mix PET | C4: 1 | D4: 220
A5: Aug 2026 | B5: 500 ml Pure PET | C5: 37 | D5: 11840
A6: Sep 2026 | B6: 1500 ml Mix PET | C6: 14 | D6: 2800
A7: Sep 2026 | B7: 1500 ml Pure PET | C7: 124 | D7: 38440
A8: Sep 2026 | B8: 500 ml Mix PET | C8: 12 | D8: 2640
A9: Sep 2026 | B9: 500 ml Pure PET | C9: 88 | D9: 28160
A10: Oct 2026 | B10: 1500 ml Mix PET | C10: 17 | D10: 3400
A11: Oct 2026 | B11: 1500 ml Pure PET | C11: 107 | D11: 32370
A12: Oct 2026 | B12: 500 ml Mix PET | C12: 17 | D12: 3740
A13: Oct 2026 | B13: 500 ml Pure PET | C13: 141 | D13: 44810
B14: TOTAL PRODUCT SALES | C14: =SUM(C2:C13) -> 645 | D14: =SUM(D2:D13) -> 191210

Sheet Expenses_and_Draws
A1: Entry Code | B1: Date | C1: Account / Category | D1: Type | E1: Plant Operating Expense (PKR) | F1: Personal Owner Draw (PKR) | G1: Total Outflow (PKR)
A2: E#1 | B2: 21 Aug 2026 | C2: Fuel Cost | D2: DIRECT | E2: 1500 | F2: 0 | G2: =E2+F2 -> 1500
A3: E#2 | B3: 23 Aug 2026 | C3: Fuel Cost | D3: DIRECT | E3: 80 | F3: 0 | G3: =E3+F3 -> 80
A4: E#3 | B4: 24 Aug 2026 | C4: Fuel Cost | D4: DIRECT | E4: 800 | F4: 0 | G4: =E4+F4 -> 800
A5: E#4 | B5: 01 Sep 2026 | C5: Fuel Cost | D5: DIRECT | E5: 50 | F5: 0 | G5: =E5+F5 -> 50
A6: E#5 | B6: 03 Sep 2026 | C6: Fuel Cost | D6: DIRECT | E6: 80 | F6: 0 | G6: =E6+F6 -> 80
A7: E#6 | B7: 07 Sep 2026 | C7: Fuel Cost | D7: DIRECT | E7: 90 | F7: 0 | G7: =E7+F7 -> 90
A8: E#7 | B8: 08 Sep 2026 | C8: Fuel Cost | D8: DIRECT | E8: 250 | F8: 0 | G8: =E8+F8 -> 250
A9: E#8 | B9: 09 Sep 2026 | C9: Fuel Cost | D9: DIRECT | E9: 400 | F9: 0 | G9: =E9+F9 -> 400
A10: E#9 | B10: 09 Sep 2026 | C10: Fuel Cost | D10: DIRECT | E10: 300 | F10: 0 | G10: =E10+F10 -> 300
A11: E#10 | B11: 10 Sep 2026 | C11: Fuel Cost | D11: DIRECT | E11: 250 | F11: 0 | G11: =E11+F11 -> 250
A12: E#11 | B12: 13 Sep 2026 | C12: Fuel Cost | D12: DIRECT | E12: 250 | F12: 0 | G12: =E12+F12 -> 250
A13: E#12 | B13: 15 Sep 2026 | C13: Fuel Cost | D13: DIRECT | E13: 200 | F13: 0 | G13: =E13+F13 -> 200
... A28: E#28 | B28: 20 Oct 2026 | C28: Fuel Cost | D28: DIRECT | E28: 300 | F28: 0 | G28: =E28+F28 -> 300
C29: TOTALS | E29: =SUM(E2:E28) -> 11760 | F29: =SUM(F2:F28) -> 20350 | G29: =SUM(G2:G28) -> 32110

Sheet Unpaid_Invoices
A1: Sr No. | B1: Customer Name | C1: Invoice No. | D1: Invoice Amount (PKR) | E1: Payments Received (PKR) | F1: Balance Pending (PKR)
A2: 1 | B2: Abdullah Cold Corner | C2: INV#79 | D2: 3380 | E2: 0 | F2: =D2-E2 -> 3380
A3: 2 | B3: Adnan Pan Shop | C3: INV#91 | D3: 2100 | E3: 0 | F3: =D3-E3 -> 2100
A4: 3 | B4: Butt Tobacco Shop | C4: INV#81 | D4: 1240 | E4: 500 | F4: =D4-E4 -> 740
A5: 4 | B5: Friends Pharmacy | C5: INV#78 | D5: 3150 | E5: 0 | F5: =D5-E5 -> 3150
A6: 5 | B6: Hussain Farooq | C6: INV#33 | D6: 4300 | E6: 4000 | F6: =D6-E6 -> 300
A7: 6 | B7: Ibrahim Pharmacy | C7: INV#75 | D7: 3150 | E7: 2000 | F7: =D7-E7 -> 1150
A8: 7 | B8: Lasani Phamacy | C8: INV#88 | D8: 1550 | E8: 0 | F8: =D8-E8 -> 1550
A9: 8 | B9: Naveed Burger Shop | C9: INV#80 | D9: 15000 | E9: 8000 | F9: =D9-E9 -> 7000
A10: 9 | B10: TT Butt Pan Shop | C10: INV#82 | D10: 9100 | E10: 0 | F10: =D10-E10 -> 9100
B11: TOTAL UNPAID RECEIVABLES | D11: =SUM(D2:D10) -> 42970 | E11: =SUM(E2:E10) -> 14500 | F11: =SUM(F2:F10) -> 28470

Sheet Direct_Operating_Expenses
A1: Entry ID | B1: Date | C1: Expense Account / Description | D1: Category Type | E1: Amount (PKR)
A2: E#1 | B2: 21 Aug 2026 | C2: Fuel Cost | D2: DIRECT | E2: 1500
A3: E#2 | B3: 23 Aug 2026 | C3: Fuel Cost | D3: DIRECT | E3: 80
A4: E#3 | B4: 24 Aug 2026 | C4: Fuel Cost | D4: DIRECT | E4: 800
A5: E#4 | B5: 01 Sep 2026 | C5: Fuel Cost | D5: DIRECT | E5: 50
A6: E#5 | B6: 03 Sep 2026 | C6: Fuel Cost | D6: DIRECT | E6: 80
A7: E#6 | B7: 07 Sep 2026 | C7: Fuel Cost | D7: DIRECT | E7: 90
A8: E#7 | B8: 08 Sep 2026 | C8: Fuel Cost | D8: DIRECT | E8: 250
A9: E#8 | B9: 09 Sep 2026 | C9: Fuel Cost | D9: DIRECT | E9: 400
A10: E#9 | B10: 09 Sep 2026 | C10: Fuel Cost | D10: DIRECT | E10: 300
A11: E#10 | B11: 10 Sep 2026 | C11: Fuel Cost | D11: DIRECT | E11: 250
A12: E#11 | B12: 13 Sep 2026 | C12: Fuel Cost | D12: DIRECT | E12: 250
A13: E#12 | B13: 15 Sep 2026 | C13: Fuel Cost | D13: DIRECT | E13: 200
... A26: E#28 | B26: 20 Oct 2026 | C26: Fuel Cost | D26: DIRECT | E26: 300
C27: TOTAL OPERATING EXPENSES | E27: =SUM(E2:E26) -> 11760

Sheet Owners_Draws
A1: Entry ID | B1: Date | C1: Description / Account | D1: Category Type | E1: Amount Withdrawn (PKR)
A2: E#15 | B2: 17 Sep 2026 | C2: Profit Deducted | D2: INDIRECT / OWNER DRAW | E2: 10350
A3: E#19 | B3: 03 Oct 2026 | C3: Profit Deducted | D3: INDIRECT / OWNER DRAW | E3: 10000
C4: TOTAL OWNER DRAWS | E4: =SUM(E2:E3) -> 20350
